porter2/__init__.py
porter2/surgebase/__init__.py
porter2/surgebase/_porter2.bz
porter2/surgebase/_porter2.h
porter2/surgebase/zipper.py
porter2-0.1.1.dist-info/LICENSE
porter2-0.1.1.dist-info/METADATA
porter2-0.1.1.dist-info/WHEEL
porter2-0.1.1.dist-info/top_level.txt
porter2-0.1.1.dist-info/RECORD
