Metadata-Version: 2.1
Name: porter2
Version: 0.1.1
Summary: A python wrapper around surgebase's Go implimentation of the Porter2 stemmer
Home-page: https://github.com/kajuberdut/porter2
Author: Patrick Shechet
Author-email: patrick.shechet@gmail.com
License: Apache License 2.0
Platform: UNKNOWN
Classifier: Natural Language :: English
Classifier: Topic :: Text Processing :: Linguistic
